CommentFetcher-0.3.2.dist-info/METADATA
CommentFetcher-0.3.2.dist-info/RECORD
CommentFetcher-0.3.2.dist-info/WHEEL
CommentFetcher-0.3.2.dist-info/top_level.txt
comment_fetcher/__init__.py
